{"available": true, "buy_brokers": [{"rank": 1, "broker": "키움증권", "qty": 38037, "share": 20.13, "is_foreign": false}, {"rank": 2, "broker": "NH투자증권", "qty": 36501, "share": 19.32, "is_foreign": false}, {"rank": 3, "broker": "한국증권", "qty": 22644, "share": 11.98, "is_foreign": false}, {"rank": 4, "broker": "미래에셋증권", "qty": 22269, "share": 11.78, "is_foreign": false}, {"rank": 5, "broker": "KB증권", "qty": 11839, "share": 6.26, "is_foreign": false}], "sell_brokers": [{"rank": 1, "broker": "신한증권", "qty": 41700, "share": 22.07, "is_foreign": false}, {"rank": 2, "broker": "한국증권", "qty": 19396, "share": 10.26, "is_foreign": false}, {"rank": 3, "broker": "대신증권", "qty": 15126, "share": 8.0, "is_foreign": false}, {"rank": 4, "broker": "삼성증권", "qty": 14338, "share": 7.59, "is_foreign": false}, {"rank": 5, "broker": "키움증권", "qty": 11833, "share": 6.26, "is_foreign": false}], "global": {"buy_qty": 0, "sell_qty": 10808, "net_qty": -10808, "buy_share": 0.0, "sell_share": 5.72}, "total_volume": 188976}